ibmdbpy4nps/__init__.py
ibmdbpy4nps/aggregation.py
ibmdbpy4nps/base.py
ibmdbpy4nps/entropy.py
ibmdbpy4nps/exceptions.py
ibmdbpy4nps/filtering.py
ibmdbpy4nps/frame.py
ibmdbpy4nps/geoFrame.py
ibmdbpy4nps/geoSeries.py
ibmdbpy4nps/indexing.py
ibmdbpy4nps/internals.py
ibmdbpy4nps/series.py
ibmdbpy4nps/sql.py
ibmdbpy4nps/statistics.py
ibmdbpy4nps/utils.py
ibmdbpy4nps/ae/__init__.py
ibmdbpy4nps/ae/apply.py
ibmdbpy4nps/ae/groupedapply.py
ibmdbpy4nps/ae/install.py
ibmdbpy4nps/ae/result_builder.py
ibmdbpy4nps/ae/shaper.py
ibmdbpy4nps/ae/tapply.py
ibmdbpy4nps/ae/tapply_class.py
ibmdbpy4nps/feature_selection/__init__.py
ibmdbpy4nps/feature_selection/chisquared.py
ibmdbpy4nps/feature_selection/correlation.py
ibmdbpy4nps/feature_selection/discretize.py
ibmdbpy4nps/feature_selection/entropy.py
ibmdbpy4nps/feature_selection/gain_ratio.py
ibmdbpy4nps/feature_selection/gini.py
ibmdbpy4nps/feature_selection/info_gain.py
ibmdbpy4nps/feature_selection/private.py
ibmdbpy4nps/feature_selection/symmetric_uncertainty.py
ibmdbpy4nps/feature_selection/tstats.py
ibmdbpy4nps/learn/__init__.py
ibmdbpy4nps/learn/association_rules.py
ibmdbpy4nps/learn/kmeans.py
ibmdbpy4nps/learn/naive_bayes.py
ibmdbpy4nps/sampledata/__init__.py
ibmdbpy4nps/sampledata/iris.py
ibmdbpy4nps/sampledata/iris.txt
ibmdbpy4nps/sampledata/swiss.py
ibmdbpy4nps/sampledata/swiss.txt
ibmdbpy4nps/sampledata/titanic.py
ibmdbpy4nps/sampledata/titanic.txt
ibmdbpy4nps-0.2.1.9.dist-info/DESCRIPTION.rst
ibmdbpy4nps-0.2.1.9.dist-info/METADATA
ibmdbpy4nps-0.2.1.9.dist-info/RECORD
ibmdbpy4nps-0.2.1.9.dist-info/WHEEL
ibmdbpy4nps-0.2.1.9.dist-info/metadata.json
ibmdbpy4nps-0.2.1.9.dist-info/top_level.txt
