Metadata-Version: 2.0
Name: ibmdbpy4nps
Version: 0.2.1.9
Summary: Supports Custom ML/Analytics Execution Inside Netezza
Home-page: UNKNOWN
Author: IBM Corp.
Author-email: vinay.kasireddy@ibm.com,toni.bollinger@de.ibm.com
License: BSD
Requires-Dist: pandas
Requires-Dist: numpy
Requires-Dist: future
Requires-Dist: six
Requires-Dist: pypyodbc
Requires-Dist: lazy
Requires-Dist: nzpy
Provides-Extra: doc
Requires-Dist: sphinx; extra == 'doc'
Requires-Dist: ipython; extra == 'doc'
Requires-Dist: numpydoc; extra == 'doc'
Requires-Dist: sphinx-rtd-theme; extra == 'doc'
Provides-Extra: jdbc
Requires-Dist: JayDeBeApi (==1.*); extra == 'jdbc'
Requires-Dist: Jpype1 (==0.6.3); extra == 'jdbc'
Provides-Extra: test
Requires-Dist: pytest; extra == 'test'
Requires-Dist: flaky (==3.4.0); extra == 'test'
